{
  "coord": {
    "lon": -0.1257,
    "lat": 51.5085
  },
  "weather": [
    {
      "id": 804,
      "main": "Clouds",
      "description": "overcast clouds",
      "icon": "04d"
    }
  ],
  "base": "stations",
  "main": {
    "temp": 6.07,
    "feels_like": 2,
    "temp_min": 5.55,
    "temp_max": 7.49,
    "pressure": 994,
    "humidity": 87,
    "sea_level": 994,
    "grnd_level": 990
  },
  "visibility": 10000,
  "wind": {
    "speed": 6.69,
    "deg": 80
  },
  "clouds": {
    "all": 100
  },
  "dt": 1771001104,
  "sys": {
    "type": 2,
    "id": 2075535,
    "country": "GB",
    "sunrise": 1770967123,
    "sunset": 1771002655
  },
  "timezone": 0,
  "id": 2643743,
  "name": "London",
  "cod": 200,
  "_last_updated_utc": "2026-02-13T16:51:38.819Z"
}