{
  "coord": {
    "lon": -0.1257,
    "lat": 51.5085
  },
  "weather": [
    {
      "id": 802,
      "main": "Clouds",
      "description": "scattered clouds",
      "icon": "03d"
    }
  ],
  "base": "stations",
  "main": {
    "temp": 29.02,
    "feels_like": 28.37,
    "temp_min": 27.95,
    "temp_max": 29.58,
    "pressure": 1026,
    "humidity": 37,
    "sea_level": 1026,
    "grnd_level": 1023
  },
  "visibility": 10000,
  "wind": {
    "speed": 3.6,
    "deg": 260
  },
  "clouds": {
    "all": 38
  },
  "dt": 1779547803,
  "sys": {
    "type": 2,
    "id": 2075535,
    "country": "GB",
    "sunrise": 1779508696,
    "sunset": 1779566191
  },
  "timezone": 3600,
  "id": 2643743,
  "name": "London",
  "cod": 200,
  "_last_updated_utc": "2026-05-23T15:02:19.930Z"
}