{
  "coord": {
    "lon": -0.1257,
    "lat": 51.5085
  },
  "weather": [
    {
      "id": 800,
      "main": "Clear",
      "description": "clear sky",
      "icon": "01n"
    }
  ],
  "base": "stations",
  "main": {
    "temp": 12.63,
    "feels_like": 11.75,
    "temp_min": 10.57,
    "temp_max": 13.21,
    "pressure": 1015,
    "humidity": 69,
    "sea_level": 1015,
    "grnd_level": 1012
  },
  "visibility": 10000,
  "wind": {
    "speed": 2.24,
    "deg": 307,
    "gust": 6.71
  },
  "clouds": {
    "all": 3
  },
  "dt": 1781046495,
  "sys": {
    "type": 2,
    "id": 2075535,
    "country": "GB",
    "sunrise": 1781063041,
    "sunset": 1781122563
  },
  "timezone": 3600,
  "id": 2643743,
  "name": "London",
  "cod": 200,
  "_last_updated_utc": "2026-06-09T23:17:20.731Z"
}